pyftdibb/__init__.py
pyftdibb/base.py
pyftdibb/spi.py
pyftdi_bitbang-1.0.0.dist-info/LICENSE
pyftdi_bitbang-1.0.0.dist-info/METADATA
pyftdi_bitbang-1.0.0.dist-info/WHEEL
pyftdi_bitbang-1.0.0.dist-info/RECORD
