Metadata-Version: 2.1
Name: pyftdi-bitbang
Version: 1.0.0
Summary: Bit-bang protocol support for PyFtdi
License: MIT
Author: Kuba Szczodrzyński
Author-email: kuba@szczodrzynski.pl
Requires-Python: >=3.8,<4.0
Classifier: License :: OSI Approved :: MIT License
Classifier: Programming Language :: Python :: 3
Classifier: Programming Language :: Python :: 3.8
Classifier: Programming Language :: Python :: 3.9
Classifier: Programming Language :: Python :: 3.10
Classifier: Programming Language :: Python :: 3.11
Classifier: Programming Language :: Python :: 3.12
Requires-Dist: pyftdi (>=0.55.0,<0.56.0)
Requires-Dist: pyi2cflash (>=0.2.2,<0.3.0)
Requires-Dist: pyspiflash (>=0.6.3,<0.7.0)
